huaweicloudsdkorgid/__init__.py
huaweicloudsdkorgid/v1/__init__.py
huaweicloudsdkorgid/v1/orgid_async_client.py
huaweicloudsdkorgid/v1/orgid_client.py
huaweicloudsdkorgid/v1/model/__init__.py
huaweicloudsdkorgid/v1/model/cas_authentication_success_attributes.py
huaweicloudsdkorgid/v1/model/cas_service_response_authentication_failure.py
huaweicloudsdkorgid/v1/model/cas_service_response_authentication_success.py
huaweicloudsdkorgid/v1/model/service_response.py
huaweicloudsdkorgid/v1/model/show_oauth2_token_request.py
huaweicloudsdkorgid/v1/model/show_oauth2_token_request_body.py
huaweicloudsdkorgid/v1/model/show_oauth2_token_response.py
huaweicloudsdkorgid/v1/model/show_oauth2_user_info_request.py
huaweicloudsdkorgid/v1/model/show_oauth2_user_info_response.py
huaweicloudsdkorgid/v1/model/validate_service_request.py
huaweicloudsdkorgid/v1/model/validate_service_response.py
huaweicloudsdkorgid/v1/region/__init__.py
huaweicloudsdkorgid/v1/region/orgid_region.py
huaweicloudsdkorgid-3.1.184.dist-info/METADATA
huaweicloudsdkorgid-3.1.184.dist-info/WHEEL
huaweicloudsdkorgid-3.1.184.dist-info/licenses/LICENSE
huaweicloudsdkorgid-3.1.184.dist-info/RECORD
